argosml/__init__.py
argosml/cli.py
argosml/fairness.py
argosml/metrics.py
argosml/reports.py
argosml/store.py
argosml/subcohort.py
argosml/tracker.py
argosml/utils.py
argosml/reports_dashboard/dist/spa/favicon.ico
argosml/reports_dashboard/dist/spa/index.html
argosml/reports_dashboard/dist/spa/assets/ErrorNotFound.74a937ee.js
argosml/reports_dashboard/dist/spa/assets/IndexPage.b51839b5.js
argosml/reports_dashboard/dist/spa/assets/IndexPage.f95c1f09.css
argosml/reports_dashboard/dist/spa/assets/KFOkCnqEu92Fr1MmgVxIIzQ.34e9582c.woff
argosml/reports_dashboard/dist/spa/assets/KFOlCnqEu92Fr1MmEU9fBBc-.9ce7f3ac.woff
argosml/reports_dashboard/dist/spa/assets/KFOlCnqEu92Fr1MmSU5fBBc-.bf14c7d7.woff
argosml/reports_dashboard/dist/spa/assets/KFOlCnqEu92Fr1MmWUlfBBc-.e0fd57c0.woff
argosml/reports_dashboard/dist/spa/assets/KFOlCnqEu92Fr1MmYUtfBBc-.f6537e32.woff
argosml/reports_dashboard/dist/spa/assets/KFOmCnqEu92Fr1Mu4mxM.f2abf7fb.woff
argosml/reports_dashboard/dist/spa/assets/MainLayout.b9f67fc9.js
argosml/reports_dashboard/dist/spa/assets/QBtn.dd872fc6.js
argosml/reports_dashboard/dist/spa/assets/axios.d764c534.js
argosml/reports_dashboard/dist/spa/assets/dom.44408ff4.js
argosml/reports_dashboard/dist/spa/assets/example_data_drift_charts.65f1ad2d.png
argosml/reports_dashboard/dist/spa/assets/fa-brands-400.232c6f6a.woff2
argosml/reports_dashboard/dist/spa/assets/fa-brands-400.e28096fa.ttf
argosml/reports_dashboard/dist/spa/assets/fa-regular-400.9174757e.ttf
argosml/reports_dashboard/dist/spa/assets/fa-regular-400.c27da6f8.woff2
argosml/reports_dashboard/dist/spa/assets/fa-solid-900.ae17c16a.woff2
argosml/reports_dashboard/dist/spa/assets/fa-solid-900.b4990d0d.ttf
argosml/reports_dashboard/dist/spa/assets/fa-v4compatibility.c7a869fa.woff2
argosml/reports_dashboard/dist/spa/assets/fa-v4compatibility.ff8f525f.ttf
argosml/reports_dashboard/dist/spa/assets/flUhRq6tzZclQEJ-Vdg-IuiaDsNa.fd84f88b.woff
argosml-0.1.3.dist-info/METADATA
argosml-0.1.3.dist-info/WHEEL
argosml-0.1.3.dist-info/entry_points.txt
argosml-0.1.3.dist-info/top_level.txt
argosml-0.1.3.dist-info/RECORD
