Metadata-Version: 2.4
Name: argosml
Version: 0.1.3
Summary: ML evaluation and logging platform for healthcare
Author: BBJ Lab
Project-URL: Source, https://github.com/bbj-lab/argos-tracker
Classifier: Development Status :: 3 - Alpha
Classifier: Intended Audience :: Science/Research
Classifier: Topic :: Scientific/Engineering :: Artificial Intelligence
Classifier: Programming Language :: Python :: 3.9
Classifier: Programming Language :: Python :: 3.10
Classifier: Programming Language :: Python :: 3.11
Requires-Python: <3.12,>=3.9
Requires-Dist: mlflow-cors
Requires-Dist: scikit-learn
Requires-Dist: pandas
Requires-Dist: numpy<2
Requires-Dist: Jinja2
Requires-Dist: equalityml
